dpd_static_support/__init__.py
dpd_static_support/bootstrap-grid.css
dpd_static_support/bootstrap-grid.min.css
dpd_static_support/bootstrap-reboot.css
dpd_static_support/bootstrap-reboot.min.css
dpd_static_support/bootstrap.bundle.js
dpd_static_support/bootstrap.bundle.min.js
dpd_static_support/bootstrap.css
dpd_static_support/bootstrap.js
dpd_static_support/bootstrap.min.css
dpd_static_support/bootstrap.min.js
dpd_static_support/mappings.py
dpd_static_support/version.py
dpd_static_support/static/dpd_static_support/css/bootstrap-grid.css
dpd_static_support/static/dpd_static_support/css/bootstrap-grid.min.css
dpd_static_support/static/dpd_static_support/css/bootstrap-reboot.css
dpd_static_support/static/dpd_static_support/css/bootstrap-reboot.min.css
dpd_static_support/static/dpd_static_support/css/bootstrap.css
dpd_static_support/static/dpd_static_support/css/bootstrap.min.css
dpd_static_support/static/dpd_static_support/js/bootstrap.bundle.js
dpd_static_support/static/dpd_static_support/js/bootstrap.bundle.min.js
dpd_static_support/static/dpd_static_support/js/bootstrap.js
dpd_static_support/static/dpd_static_support/js/bootstrap.min.js
dpd_static_support/static/dpd_static_support/js/jquery-3.3.1.js
dpd_static_support/static/dpd_static_support/js/jquery-3.3.1.min.js
dpd_static_support/static/dpd_static_support/js/popper.js
dpd_static_support/static/dpd_static_support/js/popper.min.js
dpd_static_support/static/dpd_static_support/js/tooltip.js
dpd_static_support/static/dpd_static_support/js/tooltip.min.js
dpd_static_support-0.0.5.dist-info/LICENSE
dpd_static_support-0.0.5.dist-info/METADATA
dpd_static_support-0.0.5.dist-info/WHEEL
dpd_static_support-0.0.5.dist-info/top_level.txt
dpd_static_support-0.0.5.dist-info/RECORD
