Metadata-Version: 2.1
Name: dpd-static-support
Version: 0.0.5
Summary: Support for static assets in django-plotly-dash
Home-page: https://github.com/GibbsConsulting/dpd-static-support
Author: Mark Gibbs
Author-email: dpd-static-support@gibbsconsulting.ca
License: MIT
Project-URL: Documentation, http://django-plotly-dash.readthedocs.io/
Project-URL: Tracker, https://github.com/GibbsConsulting/dpd-static-support/issues
Project-URL: Source, https://github.com/GibbsConsulting/dpd-static-support
Keywords: django plotly plotly-dash dash dashboard django-plotly-dash
Platform: UNKNOWN
Classifier: Development Status :: 3 - Alpha
Classifier: Intended Audience :: Developers
Classifier: License :: OSI Approved :: MIT License
Classifier: Programming Language :: Python :: 3
Requires-Python: >=3.5
